[
  {
    "title": "CyberVision",
    "description": "CyberVision is a massive Cyberpunk 2077 modlist with over 1500 mods, designed for immersive gameplay and visual fidelity. Focuses on roleplay, realism, and quality of life, supporting English and French profiles. Works best on Very Hard difficulty.",
    "author": "Neishin",
    "maintainers": [
      "github/Neishinlol"
    ],
    "game": "cyberpunk2077",
    "official": true,
    "tags": [
      "Steam",
      "GOG",
      "Combat Overhaul",
      "Total Overhaul"
    ],
    "nsfw": false,
    "utility_list": false,
    "image_contains_title": true,
    "DisplayVersionOnlyInInstallerView": false,
    "force_down": false,
    "links": {
      "image": "https://i.ibb.co/99DKNCwt/Cybervision.jpg",
      "readme": "https://github.com/Neishinlol/CyberVision/blob/main/README.md",
      "download": "https://authored-files.wabbajack.org/CyberVision.wabbajack_2cd2daa9-527a-471e-8156-18971b6459f8",
      "machineURL": "NeishinCyberVision",
      "discordURL": "https://discord.com/invite/WSFgf5S7wS",
      "websiteURL": "https://www.nexusmods.com/cyberpunk2077/mods/27691",
      "nexusCollection": null
    },
    "download_metadata": {
      "Hash": "SmSjHIBjn50=",
      "Size": 7747930,
      "NumberOfArchives": 1844,
      "SizeOfArchives": 82484519469,
      "NumberOfInstalledFiles": 14257,
      "SizeOfInstalledFiles": 79923252100,
      "TotalSize": 162407771569
    },
    "version": "3.0.1",
    "dateCreated": "1970-01-01T00:00:00Z",
    "dateUpdated": "2026-07-08T20:39:09.6235851Z",
    "repositoryName": ""
  }
]